MANIFEST.in
README.md
build.py
requirements-dev.txt
requirements.txt
setup.py
crypto_info/base.py
crypto_info/coins.py
crypto_info/exchanges.py
crypto_info/table.py
crypto_info.egg-info/PKG-INFO
crypto_info.egg-info/SOURCES.txt
crypto_info.egg-info/dependency_links.txt
crypto_info.egg-info/requires.txt
crypto_info.egg-info/top_level.txt
crypto_info/source/assets/logos/coins/black/$pac.png
crypto_info/source/assets/logos/coins/black/0xbtc.png
crypto_info/source/assets/logos/coins/black/1inch.png
crypto_info/source/assets/logos/coins/black/2give.png
crypto_info/source/assets/logos/coins/black/aave.png
crypto_info/source/assets/logos/coins/black/abt.png
crypto_info/source/assets/logos/coins/black/act.png
crypto_info/source/assets/logos/coins/black/actn.png
crypto_info/source/assets/logos/coins/black/ada.png
crypto_info/source/assets/logos/coins/black/add.png
crypto_info/source/assets/logos/coins/black/adx.png
crypto_info/source/assets/logos/coins/black/ae.png
crypto_info/source/assets/logos/coins/black/aeon.png
crypto_info/source/assets/logos/coins/black/aeur.png
crypto_info/source/assets/logos/coins/black/agi.png
crypto_info/source/assets/logos/coins/black/agrs.png
crypto_info/source/assets/logos/coins/black/aion.png
crypto_info/source/assets/logos/coins/black/algo.png
crypto_info/source/assets/logos/coins/black/amb.png
crypto_info/source/assets/logos/coins/black/amp.png
crypto_info/source/assets/logos/coins/black/ampl.png
crypto_info/source/assets/logos/coins/black/ankr.png
crypto_info/source/assets/logos/coins/black/ant.png
crypto_info/source/assets/logos/coins/black/ape.png
crypto_info/source/assets/logos/coins/black/apex.png
crypto_info/source/assets/logos/coins/black/appc.png
crypto_info/source/assets/logos/coins/black/ardr.png
crypto_info/source/assets/logos/coins/black/arg.png
crypto_info/source/assets/logos/coins/black/ark.png
crypto_info/source/assets/logos/coins/black/arn.png
crypto_info/source/assets/logos/coins/black/arnx.png
crypto_info/source/assets/logos/coins/black/ary.png
crypto_info/source/assets/logos/coins/black/ast.png
crypto_info/source/assets/logos/coins/black/atlas.png
